README.md
setup.py
life/__init__.py
life/base/__init__.py
life/base/q_learning.py
life/base/sarsa.py
life/base/trainer.py
life/dqn/__init__.py
life/dqn/dqn.py
life/dqn/dqn_improved.py
life/dqn/trainer.py
life/imitation/__init__.py
life/imitation/bc.py
life/imitation/gail.py
life/imitation/trainer.py
life/policy/__init__.py
life/policy/ddpg.py
life/policy/ppo.py
life/policy/reinforce.py
life/policy/sac.py
life/policy/trainer.py
life/utils/__init__.py
life/utils/calculator.py
life/utils/cont2disp.py
life/utils/replay/__init__.py
life/utils/replay/per_replay_buffer.py
life/utils/replay/replay_buffer.py
rllife.egg-info/PKG-INFO
rllife.egg-info/SOURCES.txt
rllife.egg-info/dependency_links.txt
rllife.egg-info/top_level.txt