Metadata-Version: 2.1
Name: rllife
Version: 1.0.3
Summary: a reinforce learning library, support both win and linux
Author: Yuhang Zhou
Author-email: neutjuzyh@gmail.com
Keywords: python,pytorch,reinforce learning,deep learning,DQN,QLearning,DDPG,algorithm
Classifier: Development Status :: 1 - Planning
Classifier: Intended Audience :: Developers
Classifier: Programming Language :: Python :: 3
Classifier: Operating System :: Unix
Classifier: Operating System :: MacOS :: MacOS X
Classifier: Operating System :: Microsoft :: Windows
